{"duration": 0.016303062438964844, "input_args": {"url": "'http://future-hgx-1'", "ports": "(7140, 7141, 7142, 7143)", "**": "{'headers': {'Content-Type': 'application/json'}, 'json': {'inputs': \"Given a snippet from a job vacancy, identify all the ESCO job skills mentioned. Always return skills.\\n\\n---\\n\\nFollow the following format.\\n\\nVacancy: ${text}\\nReasoning: Let's think step by step in order to ${produce the output}. We ...\\nSkills: list of comma-separated ESCO skills\\n\\n---\\n\\nVacancy: You will be responsible for the general management and development of the employees for budget and resource allocation and for ensuring timely and efficient project execution with high quality results .\\nReasoning: Let's think step by step in order to identify the ESCO job skills. We first split the text into words, then we filter out the words that are not ESCO job skills. We then return the list of ESCO job skills.\\nSkills: general management, development, employees, budget, resource allocation, project execution, quality results\\n\\n---\\n\\nVacancy: You have a proactive mindset and the ability to keep an overview in stressed situations\\nReasoning: Let's think step by step in order to\", 'parameters': {'do_sample': False, 'best_of': 1, 'details': False, 'temperature': 0.1, 'max_new_tokens': 150, 'top_p': 0.97, 'num_return_sequences': 1, 'stop': ('\\n\\n',)}}}"}, "time": 1706595856.0406754}